{
  "TranslationProperties": {
    "Name": "server.hyflask.items.Scroll_FlaskEffect_JumpHeight_T1.name",
    "Description": "server.hyflask.items.Scroll_FlaskEffect_JumpHeight_T1.description"
  },
  "Icon": "Icons/ItemsGenerated/Scroll_FlaskEffect_JumpHeight_T1.png",
  "Model": "Items/Consumables/Scrolls/EffectScroll.blockymodel",
  "Texture": "Items/Consumables/Scrolls/EffectScroll_Textures/JumpHeight/T1.png",
  "Quality": "Rare",
  "MaxStack": 99,
  "ItemLevel": 30,
  "Categories": [
    "Items.Recipes"
  ],
  "PlayerAnimationsId": "Block",
  "IconProperties": {
    "Scale": 0.6,
    "Rotation": [
      22.5,
      158,
      22.5
    ],
    "Translation": [
      -9,
      -12
    ]
  },
  "Recipe": {
    "BenchRequirement": [
      {
        "Type": "Crafting",
        "Id": "HyFlask_ResearchTable",
        "Categories": [
          "HyFlask_ResearchTable_Utility"
        ],
        "RequiredTierLevel": 2
      }
    ],
    "TimeSeconds": 5,
    "Input": [
      {
        "ItemId": "Ingredient_Bolt_Wool",
        "Quantity": 2
      },
      {
        "ItemId": "Ingredient_Life_Essence_Concentrated",
        "Quantity": 10
      },
      {
        "ItemId": "Ingredient_Feathers_Light",
        "Quantity": 25
      }
    ],
    "RequiredMemoriesLevel": 4
  },
  "Interactions": {
    "Secondary": {
      "Interactions": [
        {
          "Type": "HyFlask_LearnEffect",
          "EffectId": "FlaskEffect_JumpHeight_T1",
          "Next": {
            "Type": "ModifyInventory",
            "AdjustHeldItemQuantity": -1
          }
        },
        {
          "Type": "LearnRecipe",
          "ItemId": "Scroll_FlaskEffect_JumpHeight_T2"
        }
      ]
    }
  },
  "Consumable": true,
  "Tags": {
    "Family": [
      "HyFlask",
      "FlaskEffect"
    ],
    "Type": [
      "Upgrade"
    ]
  }
}
